[
  {
    "type": "constructor",
    "inputs": [
      {
        "name": "usdcToken",
        "type": "address",
        "internalType": "contract IERC20"
      },
      {
        "name": "_priceReader",
        "type": "address",
        "internalType": "contract PythPriceReader"
      },
      {
        "name": "_logBook",
        "type": "address",
        "internalType": "contract ILogBook"
      },
      {
        "name": "_agent",
        "type": "address",
        "internalType": "address"
      },
      {
        "name": "_slippageBps",
        "type": "uint256",
        "internalType": "uint256"
      },
      {
        "name": "_wmon",
        "type": "address",
        "internalType": "contract IWMON"
      }
    ],
    "stateMutability": "nonpayable"
  },
  {
    "type": "receive",
    "stateMutability": "payable"
  },
  {
    "type": "function",
    "name": "BPS_BAND",
    "inputs": [],
    "outputs": [
      {
        "name": "",
        "type": "uint256",
        "internalType": "uint256"
      }
    ],
    "stateMutability": "view"
  },
  {
    "type": "function",
    "name": "BPS_TARGET",
    "inputs": [],
    "outputs": [
      {
        "name": "",
        "type": "uint256",
        "internalType": "uint256"
      }
    ],
    "stateMutability": "view"
  },
  {
    "type": "function",
    "name": "agent",
    "inputs": [],
    "outputs": [
      {
        "name": "",
        "type": "address",
        "internalType": "address"
      }
    ],
    "stateMutability": "view"
  },
  {
    "type": "function",
    "name": "allocateToLp",
    "inputs": [
      {
        "name": "monAmount",
        "type": "uint256",
        "internalType": "uint256"
      },
      {
        "name": "usdcAmount",
        "type": "uint256",
        "internalType": "uint256"
      },
      {
        "name": "tickLower",
        "type": "int24",
        "internalType": "int24"
      },
      {
        "name": "tickUpper",
        "type": "int24",
        "internalType": "int24"
      }
    ],
    "outputs": [],
    "stateMutability": "nonpayable"
  },
  {
    "type": "function",
    "name": "allowance",
    "inputs": [
      {
        "name": "owner",
        "type": "address",
        "internalType": "address"
      },
      {
        "name": "spender",
        "type": "address",
        "internalType": "address"
      }
    ],
    "outputs": [
      {
        "name": "",
        "type": "uint256",
        "internalType": "uint256"
      }
    ],
    "stateMutability": "view"
  },
  {
    "type": "function",
    "name": "approve",
    "inputs": [
      {
        "name": "spender",
        "type": "address",
        "internalType": "address"
      },
      {
        "name": "value",
        "type": "uint256",
        "internalType": "uint256"
      }
    ],
    "outputs": [
      {
        "name": "",
        "type": "bool",
        "internalType": "bool"
      }
    ],
    "stateMutability": "nonpayable"
  },
  {
    "type": "function",
    "name": "asset",
    "inputs": [],
    "outputs": [
      {
        "name": "",
        "type": "address",
        "internalType": "address"
      }
    ],
    "stateMutability": "view"
  },
  {
    "type": "function",
    "name": "balanceOf",
    "inputs": [
      {
        "name": "account",
        "type": "address",
        "internalType": "address"
      }
    ],
    "outputs": [
      {
        "name": "",
        "type": "uint256",
        "internalType": "uint256"
      }
    ],
    "stateMutability": "view"
  },
  {
    "type": "function",
    "name": "collectLpFees",
    "inputs": [],
    "outputs": [],
    "stateMutability": "nonpayable"
  },
  {
    "type": "function",
    "name": "convertToAssets",
    "inputs": [
      {
        "name": "shares",
        "type": "uint256",
        "internalType": "uint256"
      }
    ],
    "outputs": [
      {
        "name": "",
        "type": "uint256",
        "internalType": "uint256"
      }
    ],
    "stateMutability": "view"
  },
  {
    "type": "function",
    "name": "convertToShares",
    "inputs": [
      {
        "name": "assets",
        "type": "uint256",
        "internalType": "uint256"
      }
    ],
    "outputs": [
      {
        "name": "",
        "type": "uint256",
        "internalType": "uint256"
      }
    ],
    "stateMutability": "view"
  },
  {
    "type": "function",
    "name": "decimals",
    "inputs": [],
    "outputs": [
      {
        "name": "",
        "type": "uint8",
        "internalType": "uint8"
      }
    ],
    "stateMutability": "view"
  },
  {
    "type": "function",
    "name": "deposit",
    "inputs": [
      {
        "name": "assets",
        "type": "uint256",
        "internalType": "uint256"
      },
      {
        "name": "receiver",
        "type": "address",
        "internalType": "address"
      }
    ],
    "outputs": [
      {
        "name": "",
        "type": "uint256",
        "internalType": "uint256"
      }
    ],
    "stateMutability": "nonpayable"
  },
  {
    "type": "function",
    "name": "depositMON",
    "inputs": [
      {
        "name": "priceUpdate",
        "type": "bytes[]",
        "internalType": "bytes[]"
      },
      {
        "name": "receiver",
        "type": "address",
        "internalType": "address"
      }
    ],
    "outputs": [
      {
        "name": "shares",
        "type": "uint256",
        "internalType": "uint256"
      }
    ],
    "stateMutability": "payable"
  },
  {
    "type": "function",
    "name": "emergencyExitAll",
    "inputs": [
      {
        "name": "triggerVenue",
        "type": "address",
        "internalType": "address"
      }
    ],
    "outputs": [],
    "stateMutability": "nonpayable"
  },
  {
    "type": "function",
    "name": "fleeToBackup",
    "inputs": [
      {
        "name": "primary",
        "type": "address",
        "internalType": "address"
      },
      {
        "name": "backup",
        "type": "address",
        "internalType": "address"
      },
      {
        "name": "shares",
        "type": "uint256",
        "internalType": "uint256"
      }
    ],
    "outputs": [],
    "stateMutability": "nonpayable"
  },
  {
    "type": "function",
    "name": "healthMonitor",
    "inputs": [],
    "outputs": [
      {
        "name": "",
        "type": "address",
        "internalType": "contract HealthMonitor"
      }
    ],
    "stateMutability": "view"
  },
  {
    "type": "function",
    "name": "legBreakdown",
    "inputs": [],
    "outputs": [
      {
        "name": "lpValue",
        "type": "uint256",
        "internalType": "uint256"
      },
      {
        "name": "parkedValue",
        "type": "uint256",
        "internalType": "uint256"
      }
    ],
    "stateMutability": "view"
  },
  {
    "type": "function",
    "name": "logBook",
    "inputs": [],
    "outputs": [
      {
        "name": "",
        "type": "address",
        "internalType": "contract ILogBook"
      }
    ],
    "stateMutability": "view"
  },
  {
    "type": "function",
    "name": "lpManager",
    "inputs": [],
    "outputs": [
      {
        "name": "",
        "type": "address",
        "internalType": "contract LpManager"
      }
    ],
    "stateMutability": "view"
  },
  {
    "type": "function",
    "name": "maxDeposit",
    "inputs": [
      {
        "name": "",
        "type": "address",
        "internalType": "address"
      }
    ],
    "outputs": [
      {
        "name": "",
        "type": "uint256",
        "internalType": "uint256"
      }
    ],
    "stateMutability": "view"
  },
  {
    "type": "function",
    "name": "maxMint",
    "inputs": [
      {
        "name": "",
        "type": "address",
        "internalType": "address"
      }
    ],
    "outputs": [
      {
        "name": "",
        "type": "uint256",
        "internalType": "uint256"
      }
    ],
    "stateMutability": "view"
  },
  {
    "type": "function",
    "name": "maxRedeem",
    "inputs": [
      {
        "name": "owner",
        "type": "address",
        "internalType": "address"
      }
    ],
    "outputs": [
      {
        "name": "",
        "type": "uint256",
        "internalType": "uint256"
      }
    ],
    "stateMutability": "view"
  },
  {
    "type": "function",
    "name": "maxWithdraw",
    "inputs": [
      {
        "name": "owner",
        "type": "address",
        "internalType": "address"
      }
    ],
    "outputs": [
      {
        "name": "",
        "type": "uint256",
        "internalType": "uint256"
      }
    ],
    "stateMutability": "view"
  },
  {
    "type": "function",
    "name": "mint",
    "inputs": [
      {
        "name": "shares",
        "type": "uint256",
        "internalType": "uint256"
      },
      {
        "name": "receiver",
        "type": "address",
        "internalType": "address"
      }
    ],
    "outputs": [
      {
        "name": "",
        "type": "uint256",
        "internalType": "uint256"
      }
    ],
    "stateMutability": "nonpayable"
  },
  {
    "type": "function",
    "name": "name",
    "inputs": [],
    "outputs": [
      {
        "name": "",
        "type": "string",
        "internalType": "string"
      }
    ],
    "stateMutability": "view"
  },
  {
    "type": "function",
    "name": "navBreakdown",
    "inputs": [],
    "outputs": [
      {
        "name": "baseUsdc",
        "type": "uint256",
        "internalType": "uint256"
      },
      {
        "name": "baseMonValue",
        "type": "uint256",
        "internalType": "uint256"
      },
      {
        "name": "lpValue",
        "type": "uint256",
        "internalType": "uint256"
      },
      {
        "name": "total",
        "type": "uint256",
        "internalType": "uint256"
      }
    ],
    "stateMutability": "view"
  },
  {
    "type": "function",
    "name": "owner",
    "inputs": [],
    "outputs": [
      {
        "name": "",
        "type": "address",
        "internalType": "address"
      }
    ],
    "stateMutability": "view"
  },
  {
    "type": "function",
    "name": "parkMon",
    "inputs": [
      {
        "name": "erc4626",
        "type": "address",
        "internalType": "address"
      },
      {
        "name": "monAmount",
        "type": "uint256",
        "internalType": "uint256"
      }
    ],
    "outputs": [],
    "stateMutability": "nonpayable"
  },
  {
    "type": "function",
    "name": "parkUsdc",
    "inputs": [
      {
        "name": "erc4626",
        "type": "address",
        "internalType": "address"
      },
      {
        "name": "usdcAmount",
        "type": "uint256",
        "internalType": "uint256"
      }
    ],
    "outputs": [],
    "stateMutability": "nonpayable"
  },
  {
    "type": "function",
    "name": "paused",
    "inputs": [],
    "outputs": [
      {
        "name": "",
        "type": "bool",
        "internalType": "bool"
      }
    ],
    "stateMutability": "view"
  },
  {
    "type": "function",
    "name": "previewDeposit",
    "inputs": [
      {
        "name": "assets",
        "type": "uint256",
        "internalType": "uint256"
      }
    ],
    "outputs": [
      {
        "name": "",
        "type": "uint256",
        "internalType": "uint256"
      }
    ],
    "stateMutability": "view"
  },
  {
    "type": "function",
    "name": "previewMint",
    "inputs": [
      {
        "name": "shares",
        "type": "uint256",
        "internalType": "uint256"
      }
    ],
    "outputs": [
      {
        "name": "",
        "type": "uint256",
        "internalType": "uint256"
      }
    ],
    "stateMutability": "view"
  },
  {
    "type": "function",
    "name": "previewRedeem",
    "inputs": [
      {
        "name": "shares",
        "type": "uint256",
        "internalType": "uint256"
      }
    ],
    "outputs": [
      {
        "name": "",
        "type": "uint256",
        "internalType": "uint256"
      }
    ],
    "stateMutability": "view"
  },
  {
    "type": "function",
    "name": "previewWithdraw",
    "inputs": [
      {
        "name": "assets",
        "type": "uint256",
        "internalType": "uint256"
      }
    ],
    "outputs": [
      {
        "name": "",
        "type": "uint256",
        "internalType": "uint256"
      }
    ],
    "stateMutability": "view"
  },
  {
    "type": "function",
    "name": "priceReader",
    "inputs": [],
    "outputs": [
      {
        "name": "",
        "type": "address",
        "internalType": "contract PythPriceReader"
      }
    ],
    "stateMutability": "view"
  },
  {
    "type": "function",
    "name": "quoteMinOut",
    "inputs": [
      {
        "name": "tokenIn",
        "type": "address",
        "internalType": "address"
      },
      {
        "name": "amountIn",
        "type": "uint256",
        "internalType": "uint256"
      },
      {
        "name": "priceE8",
        "type": "uint256",
        "internalType": "uint256"
      }
    ],
    "outputs": [
      {
        "name": "minOut",
        "type": "uint256",
        "internalType": "uint256"
      }
    ],
    "stateMutability": "view"
  },
  {
    "type": "function",
    "name": "rebalance",
    "inputs": [
      {
        "name": "router",
        "type": "address",
        "internalType": "address"
      },
      {
        "name": "swapData",
        "type": "bytes",
        "internalType": "bytes"
      },
      {
        "name": "monToUsdc",
        "type": "bool",
        "internalType": "bool"
      },
      {
        "name": "amountIn",
        "type": "uint256",
        "internalType": "uint256"
      }
    ],
    "outputs": [],
    "stateMutability": "nonpayable"
  },
  {
    "type": "function",
    "name": "redeem",
    "inputs": [
      {
        "name": "",
        "type": "uint256",
        "internalType": "uint256"
      },
      {
        "name": "",
        "type": "address",
        "internalType": "address"
      },
      {
        "name": "",
        "type": "address",
        "internalType": "address"
      }
    ],
    "outputs": [
      {
        "name": "",
        "type": "uint256",
        "internalType": "uint256"
      }
    ],
    "stateMutability": "pure"
  },
  {
    "type": "function",
    "name": "redeemInKind",
    "inputs": [
      {
        "name": "shares",
        "type": "uint256",
        "internalType": "uint256"
      },
      {
        "name": "receiver",
        "type": "address",
        "internalType": "address"
      }
    ],
    "outputs": [
      {
        "name": "usdcOut",
        "type": "uint256",
        "internalType": "uint256"
      },
      {
        "name": "monOut",
        "type": "uint256",
        "internalType": "uint256"
      }
    ],
    "stateMutability": "nonpayable"
  },
  {
    "type": "function",
    "name": "rotateParked",
    "inputs": [
      {
        "name": "from",
        "type": "address",
        "internalType": "address"
      },
      {
        "name": "to",
        "type": "address",
        "internalType": "address"
      },
      {
        "name": "shares",
        "type": "uint256",
        "internalType": "uint256"
      },
      {
        "name": "currentYieldBps",
        "type": "uint256",
        "internalType": "uint256"
      },
      {
        "name": "candidateYieldBps",
        "type": "uint256",
        "internalType": "uint256"
      },
      {
        "name": "roundTripCostBps",
        "type": "uint256",
        "internalType": "uint256"
      }
    ],
    "outputs": [],
    "stateMutability": "nonpayable"
  },
  {
    "type": "function",
    "name": "routerWhitelist",
    "inputs": [
      {
        "name": "",
        "type": "address",
        "internalType": "address"
      }
    ],
    "outputs": [
      {
        "name": "",
        "type": "bool",
        "internalType": "bool"
      }
    ],
    "stateMutability": "view"
  },
  {
    "type": "function",
    "name": "setAgent",
    "inputs": [
      {
        "name": "_agent",
        "type": "address",
        "internalType": "address"
      }
    ],
    "outputs": [],
    "stateMutability": "nonpayable"
  },
  {
    "type": "function",
    "name": "setHealthMonitor",
    "inputs": [
      {
        "name": "_hm",
        "type": "address",
        "internalType": "contract HealthMonitor"
      }
    ],
    "outputs": [],
    "stateMutability": "nonpayable"
  },
  {
    "type": "function",
    "name": "setLpManager",
    "inputs": [
      {
        "name": "_lp",
        "type": "address",
        "internalType": "contract LpManager"
      }
    ],
    "outputs": [],
    "stateMutability": "nonpayable"
  },
  {
    "type": "function",
    "name": "setPaused",
    "inputs": [
      {
        "name": "_paused",
        "type": "bool",
        "internalType": "bool"
      }
    ],
    "outputs": [],
    "stateMutability": "nonpayable"
  },
  {
    "type": "function",
    "name": "setRouterWhitelist",
    "inputs": [
      {
        "name": "router",
        "type": "address",
        "internalType": "address"
      },
      {
        "name": "allowed",
        "type": "bool",
        "internalType": "bool"
      }
    ],
    "outputs": [],
    "stateMutability": "nonpayable"
  },
  {
    "type": "function",
    "name": "setSlippageBps",
    "inputs": [
      {
        "name": "bps",
        "type": "uint256",
        "internalType": "uint256"
      }
    ],
    "outputs": [],
    "stateMutability": "nonpayable"
  },
  {
    "type": "function",
    "name": "setVaultRouter",
    "inputs": [
      {
        "name": "_vr",
        "type": "address",
        "internalType": "contract VaultRouter"
      }
    ],
    "outputs": [],
    "stateMutability": "nonpayable"
  },
  {
    "type": "function",
    "name": "shiftLpRange",
    "inputs": [
      {
        "name": "tickLower",
        "type": "int24",
        "internalType": "int24"
      },
      {
        "name": "tickUpper",
        "type": "int24",
        "internalType": "int24"
      }
    ],
    "outputs": [],
    "stateMutability": "nonpayable"
  },
  {
    "type": "function",
    "name": "slippageBps",
    "inputs": [],
    "outputs": [
      {
        "name": "",
        "type": "uint256",
        "internalType": "uint256"
      }
    ],
    "stateMutability": "view"
  },
  {
    "type": "function",
    "name": "symbol",
    "inputs": [],
    "outputs": [
      {
        "name": "",
        "type": "string",
        "internalType": "string"
      }
    ],
    "stateMutability": "view"
  },
  {
    "type": "function",
    "name": "totalAssets",
    "inputs": [],
    "outputs": [
      {
        "name": "",
        "type": "uint256",
        "internalType": "uint256"
      }
    ],
    "stateMutability": "view"
  },
  {
    "type": "function",
    "name": "totalSupply",
    "inputs": [],
    "outputs": [
      {
        "name": "",
        "type": "uint256",
        "internalType": "uint256"
      }
    ],
    "stateMutability": "view"
  },
  {
    "type": "function",
    "name": "trackedMon",
    "inputs": [],
    "outputs": [
      {
        "name": "",
        "type": "uint256",
        "internalType": "uint256"
      }
    ],
    "stateMutability": "view"
  },
  {
    "type": "function",
    "name": "trackedUsdc",
    "inputs": [],
    "outputs": [
      {
        "name": "",
        "type": "uint256",
        "internalType": "uint256"
      }
    ],
    "stateMutability": "view"
  },
  {
    "type": "function",
    "name": "transfer",
    "inputs": [
      {
        "name": "to",
        "type": "address",
        "internalType": "address"
      },
      {
        "name": "value",
        "type": "uint256",
        "internalType": "uint256"
      }
    ],
    "outputs": [
      {
        "name": "",
        "type": "bool",
        "internalType": "bool"
      }
    ],
    "stateMutability": "nonpayable"
  },
  {
    "type": "function",
    "name": "transferFrom",
    "inputs": [
      {
        "name": "from",
        "type": "address",
        "internalType": "address"
      },
      {
        "name": "to",
        "type": "address",
        "internalType": "address"
      },
      {
        "name": "value",
        "type": "uint256",
        "internalType": "uint256"
      }
    ],
    "outputs": [
      {
        "name": "",
        "type": "bool",
        "internalType": "bool"
      }
    ],
    "stateMutability": "nonpayable"
  },
  {
    "type": "function",
    "name": "unparkToBase",
    "inputs": [
      {
        "name": "erc4626",
        "type": "address",
        "internalType": "address"
      },
      {
        "name": "shares",
        "type": "uint256",
        "internalType": "uint256"
      }
    ],
    "outputs": [],
    "stateMutability": "nonpayable"
  },
  {
    "type": "function",
    "name": "vaultRouter",
    "inputs": [],
    "outputs": [
      {
        "name": "",
        "type": "address",
        "internalType": "contract VaultRouter"
      }
    ],
    "stateMutability": "view"
  },
  {
    "type": "function",
    "name": "withdraw",
    "inputs": [
      {
        "name": "",
        "type": "uint256",
        "internalType": "uint256"
      },
      {
        "name": "",
        "type": "address",
        "internalType": "address"
      },
      {
        "name": "",
        "type": "address",
        "internalType": "address"
      }
    ],
    "outputs": [
      {
        "name": "",
        "type": "uint256",
        "internalType": "uint256"
      }
    ],
    "stateMutability": "pure"
  },
  {
    "type": "function",
    "name": "wmon",
    "inputs": [],
    "outputs": [
      {
        "name": "",
        "type": "address",
        "internalType": "contract IWMON"
      }
    ],
    "stateMutability": "view"
  },
  {
    "type": "event",
    "name": "AgentSet",
    "inputs": [
      {
        "name": "agent",
        "type": "address",
        "indexed": true,
        "internalType": "address"
      }
    ],
    "anonymous": false
  },
  {
    "type": "event",
    "name": "AllocatedToLp",
    "inputs": [
      {
        "name": "priceE8",
        "type": "uint256",
        "indexed": false,
        "internalType": "uint256"
      },
      {
        "name": "monIn",
        "type": "uint256",
        "indexed": false,
        "internalType": "uint256"
      },
      {
        "name": "usdcIn",
        "type": "uint256",
        "indexed": false,
        "internalType": "uint256"
      },
      {
        "name": "tickLower",
        "type": "int24",
        "indexed": false,
        "internalType": "int24"
      },
      {
        "name": "tickUpper",
        "type": "int24",
        "indexed": false,
        "internalType": "int24"
      },
      {
        "name": "navBefore",
        "type": "uint256",
        "indexed": false,
        "internalType": "uint256"
      },
      {
        "name": "navAfter",
        "type": "uint256",
        "indexed": false,
        "internalType": "uint256"
      }
    ],
    "anonymous": false
  },
  {
    "type": "event",
    "name": "Approval",
    "inputs": [
      {
        "name": "owner",
        "type": "address",
        "indexed": true,
        "internalType": "address"
      },
      {
        "name": "spender",
        "type": "address",
        "indexed": true,
        "internalType": "address"
      },
      {
        "name": "value",
        "type": "uint256",
        "indexed": false,
        "internalType": "uint256"
      }
    ],
    "anonymous": false
  },
  {
    "type": "event",
    "name": "Deposit",
    "inputs": [
      {
        "name": "sender",
        "type": "address",
        "indexed": true,
        "internalType": "address"
      },
      {
        "name": "owner",
        "type": "address",
        "indexed": true,
        "internalType": "address"
      },
      {
        "name": "assets",
        "type": "uint256",
        "indexed": false,
        "internalType": "uint256"
      },
      {
        "name": "shares",
        "type": "uint256",
        "indexed": false,
        "internalType": "uint256"
      }
    ],
    "anonymous": false
  },
  {
    "type": "event",
    "name": "DepositedMON",
    "inputs": [
      {
        "name": "caller",
        "type": "address",
        "indexed": true,
        "internalType": "address"
      },
      {
        "name": "receiver",
        "type": "address",
        "indexed": true,
        "internalType": "address"
      },
      {
        "name": "monIn",
        "type": "uint256",
        "indexed": false,
        "internalType": "uint256"
      },
      {
        "name": "priceE8",
        "type": "uint256",
        "indexed": false,
        "internalType": "uint256"
      },
      {
        "name": "monValueUsdc",
        "type": "uint256",
        "indexed": false,
        "internalType": "uint256"
      },
      {
        "name": "shares",
        "type": "uint256",
        "indexed": false,
        "internalType": "uint256"
      }
    ],
    "anonymous": false
  },
  {
    "type": "event",
    "name": "EmergencyExit",
    "inputs": [
      {
        "name": "caller",
        "type": "address",
        "indexed": true,
        "internalType": "address"
      },
      {
        "name": "triggerVenue",
        "type": "address",
        "indexed": true,
        "internalType": "address"
      },
      {
        "name": "monToBase",
        "type": "uint256",
        "indexed": false,
        "internalType": "uint256"
      },
      {
        "name": "usdcToBase",
        "type": "uint256",
        "indexed": false,
        "internalType": "uint256"
      }
    ],
    "anonymous": false
  },
  {
    "type": "event",
    "name": "FledToBackup",
    "inputs": [
      {
        "name": "primary",
        "type": "address",
        "indexed": true,
        "internalType": "address"
      },
      {
        "name": "backup",
        "type": "address",
        "indexed": true,
        "internalType": "address"
      },
      {
        "name": "shares",
        "type": "uint256",
        "indexed": false,
        "internalType": "uint256"
      },
      {
        "name": "navBefore",
        "type": "uint256",
        "indexed": false,
        "internalType": "uint256"
      },
      {
        "name": "navAfter",
        "type": "uint256",
        "indexed": false,
        "internalType": "uint256"
      }
    ],
    "anonymous": false
  },
  {
    "type": "event",
    "name": "HealthMonitorSet",
    "inputs": [
      {
        "name": "healthMonitor",
        "type": "address",
        "indexed": true,
        "internalType": "address"
      }
    ],
    "anonymous": false
  },
  {
    "type": "event",
    "name": "LpFeesCollected",
    "inputs": [
      {
        "name": "wmonToBase",
        "type": "uint256",
        "indexed": false,
        "internalType": "uint256"
      },
      {
        "name": "usdcToBase",
        "type": "uint256",
        "indexed": false,
        "internalType": "uint256"
      }
    ],
    "anonymous": false
  },
  {
    "type": "event",
    "name": "LpManagerSet",
    "inputs": [
      {
        "name": "lpManager",
        "type": "address",
        "indexed": true,
        "internalType": "address"
      }
    ],
    "anonymous": false
  },
  {
    "type": "event",
    "name": "LpRangeShifted",
    "inputs": [
      {
        "name": "priceE8",
        "type": "uint256",
        "indexed": false,
        "internalType": "uint256"
      },
      {
        "name": "tickLower",
        "type": "int24",
        "indexed": false,
        "internalType": "int24"
      },
      {
        "name": "tickUpper",
        "type": "int24",
        "indexed": false,
        "internalType": "int24"
      },
      {
        "name": "navBefore",
        "type": "uint256",
        "indexed": false,
        "internalType": "uint256"
      },
      {
        "name": "navAfter",
        "type": "uint256",
        "indexed": false,
        "internalType": "uint256"
      }
    ],
    "anonymous": false
  },
  {
    "type": "event",
    "name": "ParkedToVault",
    "inputs": [
      {
        "name": "erc4626",
        "type": "address",
        "indexed": true,
        "internalType": "address"
      },
      {
        "name": "monIn",
        "type": "uint256",
        "indexed": false,
        "internalType": "uint256"
      },
      {
        "name": "usdcIn",
        "type": "uint256",
        "indexed": false,
        "internalType": "uint256"
      },
      {
        "name": "navBefore",
        "type": "uint256",
        "indexed": false,
        "internalType": "uint256"
      },
      {
        "name": "navAfter",
        "type": "uint256",
        "indexed": false,
        "internalType": "uint256"
      }
    ],
    "anonymous": false
  },
  {
    "type": "event",
    "name": "PausedSet",
    "inputs": [
      {
        "name": "paused",
        "type": "bool",
        "indexed": false,
        "internalType": "bool"
      }
    ],
    "anonymous": false
  },
  {
    "type": "event",
    "name": "Rebalanced",
    "inputs": [
      {
        "name": "priceE8",
        "type": "uint256",
        "indexed": false,
        "internalType": "uint256"
      },
      {
        "name": "bpsBefore",
        "type": "uint256",
        "indexed": false,
        "internalType": "uint256"
      },
      {
        "name": "bpsAfter",
        "type": "uint256",
        "indexed": false,
        "internalType": "uint256"
      },
      {
        "name": "monToUsdc",
        "type": "bool",
        "indexed": false,
        "internalType": "bool"
      },
      {
        "name": "spent",
        "type": "uint256",
        "indexed": false,
        "internalType": "uint256"
      },
      {
        "name": "received",
        "type": "uint256",
        "indexed": false,
        "internalType": "uint256"
      }
    ],
    "anonymous": false
  },
  {
    "type": "event",
    "name": "RedeemedInKind",
    "inputs": [
      {
        "name": "owner",
        "type": "address",
        "indexed": true,
        "internalType": "address"
      },
      {
        "name": "receiver",
        "type": "address",
        "indexed": true,
        "internalType": "address"
      },
      {
        "name": "shares",
        "type": "uint256",
        "indexed": false,
        "internalType": "uint256"
      },
      {
        "name": "usdcOut",
        "type": "uint256",
        "indexed": false,
        "internalType": "uint256"
      },
      {
        "name": "monOut",
        "type": "uint256",
        "indexed": false,
        "internalType": "uint256"
      }
    ],
    "anonymous": false
  },
  {
    "type": "event",
    "name": "RotatedParked",
    "inputs": [
      {
        "name": "from",
        "type": "address",
        "indexed": true,
        "internalType": "address"
      },
      {
        "name": "to",
        "type": "address",
        "indexed": true,
        "internalType": "address"
      },
      {
        "name": "shares",
        "type": "uint256",
        "indexed": false,
        "internalType": "uint256"
      },
      {
        "name": "navBefore",
        "type": "uint256",
        "indexed": false,
        "internalType": "uint256"
      },
      {
        "name": "navAfter",
        "type": "uint256",
        "indexed": false,
        "internalType": "uint256"
      }
    ],
    "anonymous": false
  },
  {
    "type": "event",
    "name": "RouterWhitelisted",
    "inputs": [
      {
        "name": "router",
        "type": "address",
        "indexed": true,
        "internalType": "address"
      },
      {
        "name": "allowed",
        "type": "bool",
        "indexed": false,
        "internalType": "bool"
      }
    ],
    "anonymous": false
  },
  {
    "type": "event",
    "name": "SlippageUpdated",
    "inputs": [
      {
        "name": "slippageBps",
        "type": "uint256",
        "indexed": false,
        "internalType": "uint256"
      }
    ],
    "anonymous": false
  },
  {
    "type": "event",
    "name": "SwapExecuted",
    "inputs": [
      {
        "name": "router",
        "type": "address",
        "indexed": true,
        "internalType": "address"
      },
      {
        "name": "tokenIn",
        "type": "address",
        "indexed": false,
        "internalType": "address"
      },
      {
        "name": "tokenOut",
        "type": "address",
        "indexed": false,
        "internalType": "address"
      },
      {
        "name": "amountIn",
        "type": "uint256",
        "indexed": false,
        "internalType": "uint256"
      },
      {
        "name": "amountOut",
        "type": "uint256",
        "indexed": false,
        "internalType": "uint256"
      }
    ],
    "anonymous": false
  },
  {
    "type": "event",
    "name": "Transfer",
    "inputs": [
      {
        "name": "from",
        "type": "address",
        "indexed": true,
        "internalType": "address"
      },
      {
        "name": "to",
        "type": "address",
        "indexed": true,
        "internalType": "address"
      },
      {
        "name": "value",
        "type": "uint256",
        "indexed": false,
        "internalType": "uint256"
      }
    ],
    "anonymous": false
  },
  {
    "type": "event",
    "name": "UnparkedToBase",
    "inputs": [
      {
        "name": "erc4626",
        "type": "address",
        "indexed": true,
        "internalType": "address"
      },
      {
        "name": "shares",
        "type": "uint256",
        "indexed": false,
        "internalType": "uint256"
      },
      {
        "name": "assetsOut",
        "type": "uint256",
        "indexed": false,
        "internalType": "uint256"
      }
    ],
    "anonymous": false
  },
  {
    "type": "event",
    "name": "VaultRouterSet",
    "inputs": [
      {
        "name": "vaultRouter",
        "type": "address",
        "indexed": true,
        "internalType": "address"
      }
    ],
    "anonymous": false
  },
  {
    "type": "event",
    "name": "Withdraw",
    "inputs": [
      {
        "name": "sender",
        "type": "address",
        "indexed": true,
        "internalType": "address"
      },
      {
        "name": "receiver",
        "type": "address",
        "indexed": true,
        "internalType": "address"
      },
      {
        "name": "owner",
        "type": "address",
        "indexed": true,
        "internalType": "address"
      },
      {
        "name": "assets",
        "type": "uint256",
        "indexed": false,
        "internalType": "uint256"
      },
      {
        "name": "shares",
        "type": "uint256",
        "indexed": false,
        "internalType": "uint256"
      }
    ],
    "anonymous": false
  },
  {
    "type": "error",
    "name": "AgentBlocked",
    "inputs": []
  },
  {
    "type": "error",
    "name": "AllocSlippage",
    "inputs": [
      {
        "name": "navAfter",
        "type": "uint256",
        "internalType": "uint256"
      },
      {
        "name": "floor",
        "type": "uint256",
        "internalType": "uint256"
      }
    ]
  },
  {
    "type": "error",
    "name": "AmountExceedsTracked",
    "inputs": []
  },
  {
    "type": "error",
    "name": "AssetClassMismatch",
    "inputs": []
  },
  {
    "type": "error",
    "name": "BackupUnsafe",
    "inputs": []
  },
  {
    "type": "error",
    "name": "BadSlippage",
    "inputs": []
  },
  {
    "type": "error",
    "name": "ERC20InsufficientAllowance",
    "inputs": [
      {
        "name": "spender",
        "type": "address",
        "internalType": "address"
      },
      {
        "name": "allowance",
        "type": "uint256",
        "internalType": "uint256"
      },
      {
        "name": "needed",
        "type": "uint256",
        "internalType": "uint256"
      }
    ]
  },
  {
    "type": "error",
    "name": "ERC20InsufficientBalance",
    "inputs": [
      {
        "name": "sender",
        "type": "address",
        "internalType": "address"
      },
      {
        "name": "balance",
        "type": "uint256",
        "internalType": "uint256"
      },
      {
        "name": "needed",
        "type": "uint256",
        "internalType": "uint256"
      }
    ]
  },
  {
    "type": "error",
    "name": "ERC20InvalidApprover",
    "inputs": [
      {
        "name": "approver",
        "type": "address",
        "internalType": "address"
      }
    ]
  },
  {
    "type": "error",
    "name": "ERC20InvalidReceiver",
    "inputs": [
      {
        "name": "receiver",
        "type": "address",
        "internalType": "address"
      }
    ]
  },
  {
    "type": "error",
    "name": "ERC20InvalidSender",
    "inputs": [
      {
        "name": "sender",
        "type": "address",
        "internalType": "address"
      }
    ]
  },
  {
    "type": "error",
    "name": "ERC20InvalidSpender",
    "inputs": [
      {
        "name": "spender",
        "type": "address",
        "internalType": "address"
      }
    ]
  },
  {
    "type": "error",
    "name": "ERC4626ExceededMaxDeposit",
    "inputs": [
      {
        "name": "receiver",
        "type": "address",
        "internalType": "address"
      },
      {
        "name": "assets",
        "type": "uint256",
        "internalType": "uint256"
      },
      {
        "name": "max",
        "type": "uint256",
        "internalType": "uint256"
      }
    ]
  },
  {
    "type": "error",
    "name": "ERC4626ExceededMaxMint",
    "inputs": [
      {
        "name": "receiver",
        "type": "address",
        "internalType": "address"
      },
      {
        "name": "shares",
        "type": "uint256",
        "internalType": "uint256"
      },
      {
        "name": "max",
        "type": "uint256",
        "internalType": "uint256"
      }
    ]
  },
  {
    "type": "error",
    "name": "ERC4626ExceededMaxRedeem",
    "inputs": [
      {
        "name": "owner",
        "type": "address",
        "internalType": "address"
      },
      {
        "name": "shares",
        "type": "uint256",
        "internalType": "uint256"
      },
      {
        "name": "max",
        "type": "uint256",
        "internalType": "uint256"
      }
    ]
  },
  {
    "type": "error",
    "name": "ERC4626ExceededMaxWithdraw",
    "inputs": [
      {
        "name": "owner",
        "type": "address",
        "internalType": "address"
      },
      {
        "name": "assets",
        "type": "uint256",
        "internalType": "uint256"
      },
      {
        "name": "max",
        "type": "uint256",
        "internalType": "uint256"
      }
    ]
  },
  {
    "type": "error",
    "name": "HealthMonitorAlreadySet",
    "inputs": []
  },
  {
    "type": "error",
    "name": "InKindOnly",
    "inputs": []
  },
  {
    "type": "error",
    "name": "LpManagerAlreadySet",
    "inputs": []
  },
  {
    "type": "error",
    "name": "LpManagerUnset",
    "inputs": []
  },
  {
    "type": "error",
    "name": "MinOutNotMet",
    "inputs": [
      {
        "name": "received",
        "type": "uint256",
        "internalType": "uint256"
      },
      {
        "name": "minOut",
        "type": "uint256",
        "internalType": "uint256"
      }
    ]
  },
  {
    "type": "error",
    "name": "MonitorUnset",
    "inputs": []
  },
  {
    "type": "error",
    "name": "NativeSendFailed",
    "inputs": []
  },
  {
    "type": "error",
    "name": "NoEmergency",
    "inputs": []
  },
  {
    "type": "error",
    "name": "NotAgent",
    "inputs": []
  },
  {
    "type": "error",
    "name": "NotAuthorized",
    "inputs": []
  },
  {
    "type": "error",
    "name": "NotOwner",
    "inputs": []
  },
  {
    "type": "error",
    "name": "NotRebalanceable",
    "inputs": []
  },
  {
    "type": "error",
    "name": "NotStressed",
    "inputs": []
  },
  {
    "type": "error",
    "name": "OverSpent",
    "inputs": [
      {
        "name": "spent",
        "type": "uint256",
        "internalType": "uint256"
      },
      {
        "name": "amountIn",
        "type": "uint256",
        "internalType": "uint256"
      }
    ]
  },
  {
    "type": "error",
    "name": "Paused",
    "inputs": []
  },
  {
    "type": "error",
    "name": "ReentrancyGuardReentrantCall",
    "inputs": []
  },
  {
    "type": "error",
    "name": "RotationNotWorthwhile",
    "inputs": []
  },
  {
    "type": "error",
    "name": "RouterCallFailed",
    "inputs": [
      {
        "name": "ret",
        "type": "bytes",
        "internalType": "bytes"
      }
    ]
  },
  {
    "type": "error",
    "name": "RouterNotWhitelisted",
    "inputs": [
      {
        "name": "router",
        "type": "address",
        "internalType": "address"
      }
    ]
  },
  {
    "type": "error",
    "name": "SafeERC20FailedOperation",
    "inputs": [
      {
        "name": "token",
        "type": "address",
        "internalType": "address"
      }
    ]
  },
  {
    "type": "error",
    "name": "StopAdding",
    "inputs": []
  },
  {
    "type": "error",
    "name": "VaultRouterAlreadySet",
    "inputs": []
  },
  {
    "type": "error",
    "name": "VaultRouterUnset",
    "inputs": []
  },
  {
    "type": "error",
    "name": "ZeroDeposit",
    "inputs": []
  },
  {
    "type": "error",
    "name": "ZeroPrice",
    "inputs": []
  },
  {
    "type": "error",
    "name": "ZeroShares",
    "inputs": []
  }
]
